{"materials":[{"id":722,"path":"Resources/unity_builtin_extra\\Default-Particle","assetBundleId":-2,"data":["Default-Particle",19,170,3000,0,[["_InvFade",1]],[],[["_MainTex_ST",1,1,0,0]],[["_MainTex",20,720]],[]]},{"id":518,"path":"Resources/unity_builtin_extra\\Sprites-Default","assetBundleId":-2,"data":["Sprites-Default",19,26,3000,0,[["PixelSnap",0],["_EnableExternalAlpha",0]],[["_Color",1,1,1,1],["_RendererColor",1,1,1,1]],[["_MainTex_ST",1,1,0,0],["_Flip",1,1,1,1],["_AlphaTex_ST",1,1,0,0]],[["_MainTex",null,null],["_AlphaTex",null,null]],[]]},{"id":726,"path":"Resources/unity_builtin_extra\\Default-Material","assetBundleId":-2,"data":["Default-Material",19,66,2000,0,[["_Cutoff",0.5],["_Glossiness",0.5],["_GlossMapScale",1],["_SmoothnessTextureChannel",0],["_Metallic",0],["_SpecularHighlights",1],["_GlossyReflections",1],["_BumpScale",1],["_Parallax",0.0199999995529652],["_OcclusionStrength",1],["_DetailNormalMapScale",1],["_UVSec",0],["_Mode",0],["_SrcBlend",1],["_DstBlend",0],["_ZWrite",1]],[["_Color",1,1,1,1],["_EmissionColor",0,0,0,0.999999940395355]],[["_MainTex_ST",1,1,0,0],["_MetallicGlossMap_ST",1,1,0,0],["_BumpMap_ST",1,1,0,0],["_ParallaxMap_ST",1,1,0,0],["_OcclusionMap_ST",1,1,0,0],["_EmissionMap_ST",1,1,0,0],["_DetailMask_ST",1,1,0,0],["_DetailAlbedoMap_ST",1,1,0,0],["_DetailNormalMap_ST",1,1,0,0]],[["_MainTex",null,null],["_MetallicGlossMap",null,null],["_BumpMap",null,null],["_ParallaxMap",null,null],["_OcclusionMap",null,null],["_EmissionMap",null,null],["_DetailMask",null,null],["_DetailAlbedoMap",null,null],["_DetailNormalMap",null,null]],[["_EMISSION",1]]]},{"id":728,"path":"Resources/unity_builtin_extra\\Default-Skybox","assetBundleId":-2,"data":["Default-Skybox",19,152,1000,0,[["_SunDisk",1],["_SunSize",0.0399999991059303],["_SunSizeConvergence",5],["_AtmosphereThickness",1],["_Exposure",1.29999995231628]],[["_SkyTint",0.5,0.5,0.5,1],["_GroundColor",0.36899995803833,0.348999977111816,0.340999931097031,1]],[],[],[["_SUNDISK_SIMPLE",1]]]},{"id":732,"path":"Resources/unity_builtin_extra\\Default-Line","assetBundleId":-2,"data":["Default-Line",19,170,3000,0,[["_InvFade",1]],[],[["_MainTex_ST",1,1,0,0]],[["_MainTex",null,null]],[]]}],"shaders":[{"id":170,"assetBundleId":-2,"data":[[],"Legacy Shaders/Particles/Alpha Blended Premultiply",null,["SOFTPARTICLES_ON","STEREO_CUBEMAP_RENDER_ON","STEREO_INSTANCING_ON","STEREO_MULTIVIEW_ON","UNITY_SINGLE_PASS_STEREO","__"],[[0,0,"",0,"",0,[4,null],[0,null],[0,null],[[1,null],[10,null],[0,null]],[[1,null],[10,null],[0,null]],[14,null],[0,null],[0,null],[0,null],[255,null],[255,null],[[0,null],[0,null],[0,null],[8,null]],[[0,null],[0,null],[0,null],[8,null]],[[0,null],[0,null],[0,null],[8,null]],[["IGNOREPROJECTOR","true"],["PreviewType","Plane"],["QUEUE","Transparent"],["RenderType","Transparent"]],["SOFTPARTICLES_ON","STEREO_CUBEMAP_RENDER_ON","STEREO_INSTANCING_ON","STEREO_MULTIVIEW_ON","UNITY_SINGLE_PASS_STEREO","__"],[[["__","SOFTPARTICLES_ON"],1]],[[0,0,[],0,1,0,0],[0,0,[],2,3,1,0]],[],0]],[],[["_MainTex",4,0,0,0,0,"white",0],["_InvFade",3,1,0.00999999977648258,3,0,"",0]],null,null,0,0,0,0]},{"id":26,"assetBundleId":-2,"data":[[],"Sprites/Default",null,["PIXELSNAP_ON","ETC1_EXTERNAL_ALPHA","INSTANCING_ON","STEREO_CUBEMAP_RENDER_ON","STEREO_INSTANCING_ON","STEREO_MULTIVIEW_ON","UNITY_SINGLE_PASS_STEREO","_","__"],[[0,0,"",0,"",0,[4,null],[0,null],[0,null],[[1,null],[10,null],[0,null]],[[1,null],[10,null],[0,null]],[15,null],[0,null],[0,null],[0,null],[255,null],[255,null],[[0,null],[0,null],[0,null],[8,null]],[[0,null],[0,null],[0,null],[8,null]],[[0,null],[0,null],[0,null],[8,null]],[["CanUseSpriteAtlas","true"],["IGNOREPROJECTOR","true"],["PreviewType","Plane"],["QUEUE","Transparent"],["RenderType","Transparent"]],["ETC1_EXTERNAL_ALPHA","INSTANCING_ON","PIXELSNAP_ON","STEREO_CUBEMAP_RENDER_ON","STEREO_INSTANCING_ON","STEREO_MULTIVIEW_ON","UNITY_SINGLE_PASS_STEREO","_","__"],[[["_","ETC1_EXTERNAL_ALPHA"],1],[["__","INSTANCING_ON"],1],[["_","PIXELSNAP_ON"],1]],[[0,0,[],4,5,0,0],[0,0,[],6,7,1,0],[0,0,["PIXELSNAP_ON"],8,5,0,0],[0,0,["PIXELSNAP_ON"],9,7,1,0]],[],0]],[],[["_MainTex",4,0,0,0,0,"white",2],["_Color",0,1,1,1,1,"",0],["PixelSnap",2,0,0,0,0,"",0],["_RendererColor",0,1,1,1,1,"",1],["_Flip",1,1,1,1,1,"",1],["_AlphaTex",4,0,0,0,0,"white",2],["_EnableExternalAlpha",2,0,0,0,0,"",2]],null,null,0,0,0,0]},{"id":152,"assetBundleId":-2,"data":[[],"Skybox/Procedural",null,["_SUNDISK_HIGH_QUALITY","_SUNDISK_NONE","_SUNDISK_SIMPLE","STEREO_CUBEMAP_RENDER_ON","STEREO_INSTANCING_ON","STEREO_MULTIVIEW_ON","UNITY_SINGLE_PASS_STEREO"],[[0,0,"",0,"",0,[4,null],[0,null],[0,null],[[1,null],[0,null],[0,null]],[[1,null],[0,null],[0,null]],[15,null],[0,null],[0,null],[0,null],[255,null],[255,null],[[0,null],[0,null],[0,null],[8,null]],[[0,null],[0,null],[0,null],[8,null]],[[0,null],[0,null],[0,null],[8,null]],[["PreviewType","Skybox"],["QUEUE","Background"],["RenderType","Background"]],["STEREO_CUBEMAP_RENDER_ON","STEREO_INSTANCING_ON","STEREO_MULTIVIEW_ON","UNITY_SINGLE_PASS_STEREO","_SUNDISK_HIGH_QUALITY","_SUNDISK_NONE","_SUNDISK_SIMPLE"],[[["_SUNDISK_NONE","_SUNDISK_SIMPLE","_SUNDISK_HIGH_QUALITY"],0]],[[0,0,["_SUNDISK_NONE"],10,11,0,0],[0,0,["_SUNDISK_NONE"],12,13,1,0],[0,0,["_SUNDISK_SIMPLE"],14,15,0,0],[0,0,["_SUNDISK_SIMPLE"],16,17,1,0],[0,0,["_SUNDISK_HIGH_QUALITY"],18,19,0,0],[0,0,["_SUNDISK_HIGH_QUALITY"],20,21,1,0],[0,0,["_SUNDISK_NONE","_SUNDISK_SIMPLE"],10,11,0,0],[0,0,["_SUNDISK_NONE","_SUNDISK_SIMPLE"],12,13,1,0],[0,0,["_SUNDISK_HIGH_QUALITY","_SUNDISK_SIMPLE"],14,15,0,0],[0,0,["_SUNDISK_HIGH_QUALITY","_SUNDISK_SIMPLE"],16,17,1,0]],[],0]],[],[["_SunDisk",2,2,0,0,0,"",0],["_SunSize",3,0.0399999991059303,0,1,0,"",0],["_SunSizeConvergence",3,5,1,10,0,"",0],["_AtmosphereThickness",3,1,0,5,0,"",0],["_SkyTint",0,0.5,0.5,0.5,1,"",0],["_GroundColor",0,0.368999987840652,0.349000006914139,0.340999990701675,1,"",0],["_Exposure",3,1.29999995231628,0,8,0,"",0]],null,null,0,0,0,0]},{"id":28,"assetBundleId":-2,"data":[[],"UI/Default",null,["UNITY_UI_ALPHACLIP","UNITY_UI_CLIP_RECT","STEREO_CUBEMAP_RENDER_ON","STEREO_INSTANCING_ON","STEREO_MULTIVIEW_ON","UNITY_SINGLE_PASS_STEREO","_"],[[0,0,"Default",0,"",0,[0,"unity_GUIZTestMode"],[0,null],[0,null],[[1,null],[10,null],[0,null]],[[1,null],[10,null],[0,null]],[0,"_ColorMask"],[0,null],[0,null],[0,"_Stencil"],[0,"_StencilReadMask"],[0,"_StencilWriteMask"],[[0,"_StencilOp"],[0,null],[0,null],[0,"_StencilComp"]],[[0,null],[0,null],[0,null],[8,null]],[[0,null],[0,null],[0,null],[8,null]],[["CanUseSpriteAtlas","true"],["IGNOREPROJECTOR","true"],["PreviewType","Plane"],["QUEUE","Transparent"],["RenderType","Transparent"]],["STEREO_CUBEMAP_RENDER_ON","STEREO_INSTANCING_ON","STEREO_MULTIVIEW_ON","UNITY_SINGLE_PASS_STEREO","UNITY_UI_ALPHACLIP","UNITY_UI_CLIP_RECT","_"],[[["_","UNITY_UI_CLIP_RECT"],1],[["_","UNITY_UI_ALPHACLIP"],1]],[[0,0,[],22,23,0,0],[0,0,[],24,25,1,0],[0,0,["UNITY_UI_ALPHACLIP"],22,26,0,0],[0,0,["UNITY_UI_ALPHACLIP"],24,27,1,0],[0,0,["UNITY_UI_CLIP_RECT"],22,28,0,0],[0,0,["UNITY_UI_CLIP_RECT"],24,29,1,0],[0,0,["UNITY_UI_ALPHACLIP","UNITY_UI_CLIP_RECT"],22,30,0,0],[0,0,["UNITY_UI_ALPHACLIP","UNITY_UI_CLIP_RECT"],24,31,1,0]],[],0]],[],[["_MainTex",4,0,0,0,0,"white",2],["_Color",0,1,1,1,1,"",0],["_StencilComp",2,8,0,0,0,"",0],["_Stencil",2,0,0,0,0,"",0],["_StencilOp",2,0,0,0,0,"",0],["_StencilWriteMask",2,255,0,0,0,"",0],["_StencilReadMask",2,255,0,0,0,"",0],["_ColorMask",2,15,0,0,0,"",0],["_UseUIAlphaClip",2,0,0,0,0,"",0]],null,null,0,0,0,0]},{"id":178,"assetBundleId":-2,"data":[[],"Particles/Standard Unlit",null,["SHADOWS_DEPTH","_ALPHABLEND_ON","_ALPHAMODULATE_ON","_ALPHAPREMULTIPLY_ON","_ALPHATEST_ON","_REQUIRE_UV2","FOG_EXP","FOG_EXP2","FOG_LINEAR","_COLORADDSUBDIFF_ON","_COLORCOLOR_ON","_COLOROVERLAY_ON","_EMISSION","_FADING_ON","_NORMALMAP","INSTANCING_ON","PROCEDURAL_INSTANCING_ON","SHADOWS_CUBE","STEREO_CUBEMAP_RENDER_ON","STEREO_INSTANCING_ON","STEREO_MULTIVIEW_ON","UNITY_SINGLE_PASS_STEREO","__","_","EFFECT_BUMP","SOFTPARTICLES_ON"],[[0,0,"",0,"_GrabTexture",0,[0,null],[0,null],[0,null],[[1,null],[0,null],[0,null]],[[1,null],[0,null],[0,null]],[15,null],[0,null],[0,null],[0,null],[0,null],[0,null],[[0,null],[0,null],[0,null],[0,null]],[[0,null],[0,null],[0,null],[0,null]],[[0,null],[0,null],[0,null],[0,null]],[["LIGHTMODE","GRABPASS"]],[],[],[],[],0],[1,0,"ShadowCaster",8,"",0,[4,null],[1,null],[0,null],[[1,null],[0,null],[0,null]],[[1,null],[0,null],[0,null]],[14,null],[0,null],[0,null],[0,null],[255,null],[255,null],[[0,null],[0,null],[0,null],[8,null]],[[0,null],[0,null],[0,null],[8,null]],[[0,null],[0,null],[0,null],[8,null]],[["IGNOREPROJECTOR","true"],["LIGHTMODE","SHADOWCASTER"],["PerformanceChecks","False"],["PreviewType","Plane"],["RenderType","Opaque"],["SHADOWSUPPORT","true"]],["INSTANCING_ON","PROCEDURAL_INSTANCING_ON","SHADOWS_CUBE","SHADOWS_DEPTH","STEREO_CUBEMAP_RENDER_ON","STEREO_INSTANCING_ON","STEREO_MULTIVIEW_ON","UNITY_SINGLE_PASS_STEREO","_ALPHABLEND_ON","_ALPHAMODULATE_ON","_ALPHAPREMULTIPLY_ON","_ALPHATEST_ON","_REQUIRE_UV2","__","_"],[[["__","INSTANCING_ON","PROCEDURAL_INSTANCING_ON"],1],[["_","_ALPHATEST_ON","_ALPHABLEND_ON","_ALPHAPREMULTIPLY_ON","_ALPHAMODULATE_ON"],1],[["_","_REQUIRE_UV2"],1],[["SHADOWS_DEPTH"],0],[["SHADOWS_CUBE"],0]],[[1,0,["SHADOWS_DEPTH"],34,35,0,0],[1,0,["SHADOWS_DEPTH"],36,37,1,0],[1,0,["SHADOWS_DEPTH","_ALPHABLEND_ON"],38,39,0,0],[1,0,["SHADOWS_DEPTH","_ALPHABLEND_ON"],40,41,1,0]],[],0],[4,0,"",0,"",0,[4,null],[0,"_ZWrite"],[0,"_Cull"],[[0,"_SrcBlend"],[0,"_DstBlend"],[0,"_BlendOp"]],[[0,"_SrcBlend"],[0,"_DstBlend"],[0,"_BlendOp"]],[14,null],[0,null],[0,null],[0,null],[255,null],[255,null],[[0,null],[0,null],[0,null],[8,null]],[[0,null],[0,null],[0,null],[8,null]],[[0,null],[0,null],[0,null],[8,null]],[["IGNOREPROJECTOR","true"],["PerformanceChecks","False"],["PreviewType","Plane"],["RenderType","Opaque"]],["EFFECT_BUMP","FOG_EXP","FOG_EXP2","FOG_LINEAR","INSTANCING_ON","PROCEDURAL_INSTANCING_ON","SOFTPARTICLES_ON","STEREO_CUBEMAP_RENDER_ON","STEREO_INSTANCING_ON","STEREO_MULTIVIEW_ON","UNITY_SINGLE_PASS_STEREO","_ALPHABLEND_ON","_ALPHAMODULATE_ON","_ALPHAPREMULTIPLY_ON","_ALPHATEST_ON","_COLORADDSUBDIFF_ON","_COLORCOLOR_ON","_COLOROVERLAY_ON","_EMISSION","_FADING_ON","_NORMALMAP","_REQUIRE_UV2","__","_"],[[["__","SOFTPARTICLES_ON"],1],[["__","FOG_LINEAR","FOG_EXP","FOG_EXP2"],1],[["__","INSTANCING_ON","PROCEDURAL_INSTANCING_ON"],1],[["_","_NORMALMAP"],1],[["_","_FADING_ON"],1],[["_","_REQUIRE_UV2"],1],[["_","EFFECT_BUMP"],1]],[[4,0,[],42,43,0,0],[4,0,[],44,45,1,0],[4,0,["_FADING_ON"],46,43,0,0],[4,0,["_FADING_ON"],47,45,1,0],[4,0,["_ALPHABLEND_ON","_FADING_ON"],46,48,0,0],[4,0,["_ALPHABLEND_ON","_FADING_ON"],47,49,1,0],[4,0,["_ALPHABLEND_ON"],42,50,0,0],[4,0,["_ALPHABLEND_ON"],44,51,1,0]],[],0]],[],[["_MainTex",4,0,0,0,0,"white",0],["_Color",0,1,1,1,1,"",0],["_Cutoff",3,0.5,0,1,0,"",0],["_BumpScale",2,1,0,0,0,"",0],["_BumpMap",4,0,0,0,0,"bump",0],["_EmissionColor",0,0,0,0,1,"",0],["_EmissionMap",4,0,0,0,0,"white",0],["_DistortionStrength",2,1,0,0,0,"",0],["_DistortionBlend",3,0.5,0,1,0,"",0],["_SoftParticlesNearFadeDistance",2,0,0,0,0,"",0],["_SoftParticlesFarFadeDistance",2,1,0,0,0,"",0],["_CameraNearFadeDistance",2,1,0,0,0,"",0],["_CameraFarFadeDistance",2,2,0,0,0,"",0],["_Mode",2,0,0,0,0,"",1],["_ColorMode",2,0,0,0,0,"",1],["_FlipbookMode",2,0,0,0,0,"",1],["_LightingEnabled",2,0,0,0,0,"",1],["_DistortionEnabled",2,0,0,0,0,"",1],["_EmissionEnabled",2,0,0,0,0,"",1],["_BlendOp",2,0,0,0,0,"",1],["_SrcBlend",2,1,0,0,0,"",1],["_DstBlend",2,0,0,0,0,"",1],["_ZWrite",2,1,0,0,0,"",1],["_Cull",2,2,0,0,0,"",1],["_SoftParticlesEnabled",2,0,0,0,0,"",1],["_CameraFadingEnabled",2,0,0,0,0,"",1],["_SoftParticleFadeParams",1,0,0,0,0,"",1],["_CameraFadeParams",1,0,0,0,0,"",1],["_ColorAddSubDiff",1,0,0,0,0,"",1],["_DistortionStrengthScaled",2,0,0,0,0,"",1]],19,70,0,0,0,0]},{"id":46,"assetBundleId":-2,"data":[[],"Hidden/BlitCopy",null,["STEREO_CUBEMAP_RENDER_ON","STEREO_INSTANCING_ON","STEREO_MULTIVIEW_ON","UNITY_SINGLE_PASS_STEREO"],[[0,0,"",0,"",0,[8,null],[0,null],[0,null],[[1,null],[0,null],[0,null]],[[1,null],[0,null],[0,null]],[15,null],[0,null],[0,null],[0,null],[255,null],[255,null],[[0,null],[0,null],[0,null],[8,null]],[[0,null],[0,null],[0,null],[8,null]],[[0,null],[0,null],[0,null],[8,null]],[],["STEREO_CUBEMAP_RENDER_ON","STEREO_INSTANCING_ON","STEREO_MULTIVIEW_ON","UNITY_SINGLE_PASS_STEREO"],[],[[0,0,[],52,53,0,0],[0,0,[],54,55,1,0]],[],0]],[],[["_MainTex",4,0,0,0,0,"",0],["_Color",0,1,1,1,1,"",0]],null,null,0,0,0,0]},{"id":70,"assetBundleId":-2,"data":[[],"Legacy Shaders/VertexLit",null,["FOG_EXP","FOG_EXP2","FOG_LINEAR","POINT","SPOT","SHADOWS_DEPTH","STEREO_CUBEMAP_RENDER_ON","STEREO_INSTANCING_ON","STEREO_MULTIVIEW_ON","UNITY_SINGLE_PASS_STEREO","_","__","INSTANCING_ON","SHADOWS_CUBE"],[[0,0,"",1,"",0,[4,null],[1,null],[2,null],[[1,null],[0,null],[0,null]],[[1,null],[0,null],[0,null]],[15,null],[0,null],[0,null],[0,null],[255,null],[255,null],[[0,null],[0,null],[0,null],[8,null]],[[0,null],[0,null],[0,null],[8,null]],[[0,null],[0,null],[0,null],[8,null]],[["LIGHTMODE","Vertex"],["RenderType","Opaque"]],["FOG_EXP","FOG_EXP2","FOG_LINEAR","POINT","SPOT","STEREO_CUBEMAP_RENDER_ON","STEREO_INSTANCING_ON","STEREO_MULTIVIEW_ON","UNITY_SINGLE_PASS_STEREO","_"],[[["_","FOG_LINEAR","FOG_EXP","FOG_EXP2"],1],[["_","POINT","SPOT"],1]],[[0,0,[],165,166,0,0],[0,0,[],167,168,1,0]],[],0],[1,0,"",2,"",0,[4,null],[1,null],[2,null],[[1,null],[0,null],[0,null]],[[1,null],[0,null],[0,null]],[15,null],[0,null],[0,null],[0,null],[255,null],[255,null],[[0,null],[0,null],[0,null],[8,null]],[[0,null],[0,null],[0,null],[8,null]],[[0,null],[0,null],[0,null],[8,null]],[["LIGHTMODE","VertexLM"],["RenderType","Opaque"]],["FOG_EXP","FOG_EXP2","FOG_LINEAR","STEREO_CUBEMAP_RENDER_ON","STEREO_INSTANCING_ON","STEREO_MULTIVIEW_ON","UNITY_SINGLE_PASS_STEREO","__"],[[["__","FOG_LINEAR","FOG_EXP","FOG_EXP2"],1]],[[1,0,[],169,170,0,0],[1,0,[],171,172,1,0]],[],0],[2,0,"ShadowCaster",8,"",0,[4,null],[1,null],[2,null],[[1,null],[0,null],[0,null]],[[1,null],[0,null],[0,null]],[15,null],[0,null],[0,null],[0,null],[255,null],[255,null],[[0,null],[0,null],[0,null],[8,null]],[[0,null],[0,null],[0,null],[8,null]],[[0,null],[0,null],[0,null],[8,null]],[["LIGHTMODE","SHADOWCASTER"],["RenderType","Opaque"],["SHADOWSUPPORT","true"]],["INSTANCING_ON","SHADOWS_CUBE","SHADOWS_DEPTH","STEREO_CUBEMAP_RENDER_ON","STEREO_INSTANCING_ON","STEREO_MULTIVIEW_ON","UNITY_SINGLE_PASS_STEREO","__"],[[["__","INSTANCING_ON"],1],[["SHADOWS_DEPTH"],0],[["SHADOWS_CUBE"],0]],[[2,0,["SHADOWS_DEPTH"],34,35,0,0],[2,0,["SHADOWS_DEPTH"],36,164,1,0]],[],0]],[],[["_Color",0,1,1,1,1,"",0],["_SpecColor",0,1,1,1,1,"",0],["_Emission",0,0,0,0,0,"",0],["_Shininess",3,0.699999988079071,0.00999999977648258,1,0,"",0],["_MainTex",4,0,0,0,0,"white",0]],null,null,0,0,0,0]},{"id":66,"assetBundleId":-2,"data":[[],"Standard",null,["DIRECTIONAL","DIRLIGHTMAP_COMBINED","FOG_EXP","FOG_EXP2","FOG_LINEAR","LIGHTMAP_ON","LIGHTPROBE_SH","SHADOWS_SCREEN","SHADOWS_SHADOWMASK","VERTEXLIGHT_ON","_ALPHABLEND_ON","_ALPHAPREMULTIPLY_ON","_ALPHATEST_ON","_EMISSION","_GLOSSYREFLECTIONS_OFF","_METALLICGLOSSMAP","_NORMALMAP","_PARALLAXMAP","_SMOOTHNESS_TEXTURE_ALBEDO_CHANNEL_A","_SPECULARHIGHLIGHTS_OFF","DIRECTIONAL_COOKIE","POINT","POINT_COOKIE","SHADOWS_DEPTH","SPOT","DYNAMICLIGHTMAP_ON","INSTANCING_ON","LIGHTMAP_SHADOW_MIXING","STEREO_CUBEMAP_RENDER_ON","STEREO_INSTANCING_ON","STEREO_MULTIVIEW_ON","UNITY_SINGLE_PASS_STEREO","_DETAIL_MULX2","__","_","SHADOWS_CUBE","SHADOWS_SOFT"],[[0,0,"FORWARD",4,"",0,[4,null],[0,"_ZWrite"],[2,null],[[0,"_SrcBlend"],[0,"_DstBlend"],[0,null]],[[0,"_SrcBlend"],[0,"_DstBlend"],[0,null]],[15,null],[0,null],[0,null],[0,null],[255,null],[255,null],[[0,null],[0,null],[0,null],[8,null]],[[0,null],[0,null],[0,null],[8,null]],[[0,null],[0,null],[0,null],[8,null]],[["LIGHTMODE","FORWARDBASE"],["PerformanceChecks","False"],["RenderType","Opaque"],["SHADOWSUPPORT","true"]],["DIRECTIONAL","DIRLIGHTMAP_COMBINED","DYNAMICLIGHTMAP_ON","FOG_EXP","FOG_EXP2","FOG_LINEAR","INSTANCING_ON","LIGHTMAP_ON","LIGHTMAP_SHADOW_MIXING","LIGHTPROBE_SH","SHADOWS_SCREEN","SHADOWS_SHADOWMASK","STEREO_CUBEMAP_RENDER_ON","STEREO_INSTANCING_ON","STEREO_MULTIVIEW_ON","UNITY_SINGLE_PASS_STEREO","VERTEXLIGHT_ON","_ALPHABLEND_ON","_ALPHAPREMULTIPLY_ON","_ALPHATEST_ON","_DETAIL_MULX2","_EMISSION","_GLOSSYREFLECTIONS_OFF","_METALLICGLOSSMAP","_NORMALMAP","_PARALLAXMAP","_SMOOTHNESS_TEXTURE_ALBEDO_CHANNEL_A","_SPECULARHIGHLIGHTS_OFF","__","_"],[[["__","FOG_LINEAR","FOG_EXP","FOG_EXP2"],1],[["__","INSTANCING_ON"],1],[["_","_NORMALMAP"],1],[["_","_ALPHATEST_ON","_ALPHABLEND_ON","_ALPHAPREMULTIPLY_ON"],1],[["_","_METALLICGLOSSMAP"],1],[["_","_PARALLAXMAP"],1],[["DIRECTIONAL"],0],[["DIRECTIONAL","LIGHTPROBE_SH"],0],[["DIRECTIONAL","SHADOWS_SHADOWMASK","LIGHTPROBE_SH"],0],[["DIRECTIONAL","DYNAMICLIGHTMAP_ON"],0],[["DIRECTIONAL","LIGHTMAP_ON"],0],[["DIRECTIONAL","LIGHTMAP_ON","DYNAMICLIGHTMAP_ON"],0],[["DIRECTIONAL","LIGHTMAP_ON","LIGHTPROBE_SH"],0],[["DIRECTIONAL","LIGHTMAP_ON","LIGHTMAP_SHADOW_MIXING"],0],[["DIRECTIONAL","LIGHTMAP_ON","DYNAMICLIGHTMAP_ON","LIGHTMAP_SHADOW_MIXING"],0],[["DIRECTIONAL","LIGHTMAP_ON","LIGHTMAP_SHADOW_MIXING","LIGHTPROBE_SH"],0],[["DIRECTIONAL","DIRLIGHTMAP_COMBINED","DYNAMICLIGHTMAP_ON"],0],[["DIRECTIONAL","LIGHTMAP_ON","DIRLIGHTMAP_COMBINED"],0],[["DIRECTIONAL","LIGHTMAP_ON","DIRLIGHTMAP_COMBINED","LIGHTPROBE_SH"],0],[["DIRECTIONAL","LIGHTMAP_ON","DIRLIGHTMAP_COMBINED","DYNAMICLIGHTMAP_ON"],0],[["DIRECTIONAL","LIGHTMAP_ON","DIRLIGHTMAP_COMBINED","LIGHTMAP_SHADOW_MIXING"],0],[["DIRECTIONAL","LIGHTMAP_ON","DIRLIGHTMAP_COMBINED","LIGHTMAP_SHADOW_MIXING","LIGHTPROBE_SH"],0],[["DIRECTIONAL","LIGHTMAP_ON","DIRLIGHTMAP_COMBINED","DYNAMICLIGHTMAP_ON","LIGHTMAP_SHADOW_MIXING"],0],[["DIRECTIONAL","LIGHTMAP_ON","SHADOWS_SHADOWMASK"],0],[["DIRECTIONAL","LIGHTMAP_ON","DYNAMICLIGHTMAP_ON","SHADOWS_SHADOWMASK"],0],[["DIRECTIONAL","LIGHTMAP_ON","SHADOWS_SHADOWMASK","LIGHTPROBE_SH"],0],[["DIRECTIONAL","LIGHTMAP_ON","DIRLIGHTMAP_COMBINED","SHADOWS_SHADOWMASK"],0],[["DIRECTIONAL","LIGHTMAP_ON","DIRLIGHTMAP_COMBINED","DYNAMICLIGHTMAP_ON","SHADOWS_SHADOWMASK"],0],[["DIRECTIONAL","LIGHTMAP_ON","DIRLIGHTMAP_COMBINED","SHADOWS_SHADOWMASK","LIGHTPROBE_SH"],0],[["DIRECTIONAL","LIGHTMAP_ON","SHADOWS_SHADOWMASK","LIGHTMAP_SHADOW_MIXING"],0],[["DIRECTIONAL","LIGHTMAP_ON","DYNAMICLIGHTMAP_ON","SHADOWS_SHADOWMASK","LIGHTMAP_SHADOW_MIXING"],0],[["DIRECTIONAL","LIGHTMAP_ON","SHADOWS_SHADOWMASK","LIGHTMAP_SHADOW_MIXING","LIGHTPROBE_SH"],0],[["DIRECTIONAL","LIGHTMAP_ON","DIRLIGHTMAP_COMBINED","SHADOWS_SHADOWMASK","LIGHTMAP_SHADOW_MIXING"],0],[["DIRECTIONAL","LIGHTMAP_ON","DIRLIGHTMAP_COMBINED","DYNAMICLIGHTMAP_ON","SHADOWS_SHADOWMASK","LIGHTMAP_SHADOW_MIXING"],0],[["DIRECTIONAL","LIGHTMAP_ON","DIRLIGHTMAP_COMBINED","SHADOWS_SHADOWMASK","LIGHTMAP_SHADOW_MIXING","LIGHTPROBE_SH"],0],[["DIRECTIONAL","SHADOWS_SCREEN"],0],[["DIRECTIONAL","SHADOWS_SCREEN","LIGHTPROBE_SH"],0],[["DIRECTIONAL","DYNAMICLIGHTMAP_ON","SHADOWS_SCREEN"],0],[["DIRECTIONAL","SHADOWS_SCREEN","LIGHTMAP_SHADOW_MIXING","LIGHTPROBE_SH"],0],[["DIRECTIONAL","DYNAMICLIGHTMAP_ON","SHADOWS_SCREEN","LIGHTMAP_SHADOW_MIXING"],0],[["DIRECTIONAL","SHADOWS_SCREEN","SHADOWS_SHADOWMASK","LIGHTPROBE_SH"],0],[["DIRECTIONAL","DYNAMICLIGHTMAP_ON","SHADOWS_SCREEN","SHADOWS_SHADOWMASK"],0],[["DIRECTIONAL","SHADOWS_SCREEN","SHADOWS_SHADOWMASK","LIGHTMAP_SHADOW_MIXING","LIGHTPROBE_SH"],0],[["DIRECTIONAL","DYNAMICLIGHTMAP_ON","SHADOWS_SCREEN","SHADOWS_SHADOWMASK","LIGHTMAP_SHADOW_MIXING"],0],[["DIRECTIONAL","LIGHTMAP_ON","SHADOWS_SCREEN"],0],[["DIRECTIONAL","LIGHTMAP_ON","DYNAMICLIGHTMAP_ON","SHADOWS_SCREEN"],0],[["DIRECTIONAL","LIGHTMAP_ON","SHADOWS_SCREEN","LIGHTPROBE_SH"],0],[["DIRECTIONAL","LIGHTMAP_ON","SHADOWS_SCREEN","LIGHTMAP_SHADOW_MIXING"],0],[["DIRECTIONAL","LIGHTMAP_ON","DYNAMICLIGHTMAP_ON","SHADOWS_SCREEN","LIGHTMAP_SHADOW_MIXING"],0],[["DIRECTIONAL","LIGHTMAP_ON","SHADOWS_SCREEN","LIGHTMAP_SHADOW_MIXING","LIGHTPROBE_SH"],0],[["DIRECTIONAL","LIGHTMAP_ON","SHADOWS_SCREEN","SHADOWS_SHADOWMASK"],0],[["DIRECTIONAL","LIGHTMAP_ON","DYNAMICLIGHTMAP_ON","SHADOWS_SCREEN","SHADOWS_SHADOWMASK"],0],[["DIRECTIONAL","LIGHTMAP_ON","SHADOWS_SCREEN","SHADOWS_SHADOWMASK","LIGHTPROBE_SH"],0],[["DIRECTIONAL","LIGHTMAP_ON","SHADOWS_SCREEN","SHADOWS_SHADOWMASK","LIGHTMAP_SHADOW_MIXING"],0],[["DIRECTIONAL","LIGHTMAP_ON","DYNAMICLIGHTMAP_ON","SHADOWS_SCREEN","SHADOWS_SHADOWMASK","LIGHTMAP_SHADOW_MIXING"],0],[["DIRECTIONAL","LIGHTMAP_ON","SHADOWS_SCREEN","SHADOWS_SHADOWMASK","LIGHTMAP_SHADOW_MIXING","LIGHTPROBE_SH"],0],[["DIRECTIONAL","DIRLIGHTMAP_COMBINED","DYNAMICLIGHTMAP_ON","SHADOWS_SCREEN"],0],[["DIRECTIONAL","LIGHTMAP_ON","DIRLIGHTMAP_COMBINED","SHADOWS_SCREEN"],0],[["DIRECTIONAL","LIGHTMAP_ON","DIRLIGHTMAP_COMBINED","SHADOWS_SCREEN","LIGHTPROBE_SH"],0],[["DIRECTIONAL","LIGHTMAP_ON","DIRLIGHTMAP_COMBINED","DYNAMICLIGHTMAP_ON","SHADOWS_SCREEN"],0],[["DIRECTIONAL","LIGHTMAP_ON","DIRLIGHTMAP_COMBINED","SHADOWS_SCREEN","LIGHTMAP_SHADOW_MIXING"],0],[["DIRECTIONAL","LIGHTMAP_ON","DIRLIGHTMAP_COMBINED","SHADOWS_SCREEN","LIGHTMAP_SHADOW_MIXING","LIGHTPROBE_SH"],0],[["DIRECTIONAL","LIGHTMAP_ON","DIRLIGHTMAP_COMBINED","DYNAMICLIGHTMAP_ON","SHADOWS_SCREEN","LIGHTMAP_SHADOW_MIXING"],0],[["DIRECTIONAL","LIGHTMAP_ON","DIRLIGHTMAP_COMBINED","SHADOWS_SCREEN","SHADOWS_SHADOWMASK"],0],[["DIRECTIONAL","LIGHTMAP_ON","DIRLIGHTMAP_COMBINED","SHADOWS_SCREEN","SHADOWS_SHADOWMASK","LIGHTPROBE_SH"],0],[["DIRECTIONAL","LIGHTMAP_ON","DIRLIGHTMAP_COMBINED","DYNAMICLIGHTMAP_ON","SHADOWS_SCREEN","SHADOWS_SHADOWMASK"],0],[["DIRECTIONAL","LIGHTMAP_ON","DIRLIGHTMAP_COMBINED","SHADOWS_SCREEN","SHADOWS_SHADOWMASK","LIGHTMAP_SHADOW_MIXING"],0],[["DIRECTIONAL","LIGHTMAP_ON","DIRLIGHTMAP_COMBINED","SHADOWS_SCREEN","SHADOWS_SHADOWMASK","LIGHTMAP_SHADOW_MIXING","LIGHTPROBE_SH"],0],[["DIRECTIONAL","LIGHTMAP_ON","DIRLIGHTMAP_COMBINED","DYNAMICLIGHTMAP_ON","SHADOWS_SCREEN","SHADOWS_SHADOWMASK","LIGHTMAP_SHADOW_MIXING"],0],[["DIRECTIONAL","VERTEXLIGHT_ON"],0],[["DIRECTIONAL","VERTEXLIGHT_ON","LIGHTPROBE_SH"],0],[["DIRECTIONAL","VERTEXLIGHT_ON","DYNAMICLIGHTMAP_ON"],0],[["DIRECTIONAL","VERTEXLIGHT_ON","DIRLIGHTMAP_COMBINED","DYNAMICLIGHTMAP_ON"],0],[["DIRECTIONAL","VERTEXLIGHT_ON","SHADOWS_SCREEN"],0],[["DIRECTIONAL","VERTEXLIGHT_ON","SHADOWS_SCREEN","LIGHTPROBE_SH"],0],[["DIRECTIONAL","VERTEXLIGHT_ON","DYNAMICLIGHTMAP_ON","SHADOWS_SCREEN"],0],[["DIRECTIONAL","VERTEXLIGHT_ON","DIRLIGHTMAP_COMBINED","DYNAMICLIGHTMAP_ON","SHADOWS_SCREEN"],0],[["DIRECTIONAL","VERTEXLIGHT_ON","SHADOWS_SCREEN","LIGHTMAP_SHADOW_MIXING"],0],[["DIRECTIONAL","VERTEXLIGHT_ON","SHADOWS_SCREEN","LIGHTMAP_SHADOW_MIXING","LIGHTPROBE_SH"],0],[["DIRECTIONAL","VERTEXLIGHT_ON","DYNAMICLIGHTMAP_ON","SHADOWS_SCREEN","LIGHTMAP_SHADOW_MIXING"],0],[["DIRECTIONAL","VERTEXLIGHT_ON","DIRLIGHTMAP_COMBINED","DYNAMICLIGHTMAP_ON","SHADOWS_SCREEN","LIGHTMAP_SHADOW_MIXING"],0],[["DIRECTIONAL","VERTEXLIGHT_ON","SHADOWS_SCREEN","SHADOWS_SHADOWMASK"],0],[["DIRECTIONAL","VERTEXLIGHT_ON","SHADOWS_SCREEN","SHADOWS_SHADOWMASK","LIGHTPROBE_SH"],0],[["DIRECTIONAL","VERTEXLIGHT_ON","DYNAMICLIGHTMAP_ON","SHADOWS_SCREEN","SHADOWS_SHADOWMASK"],0],[["DIRECTIONAL","VERTEXLIGHT_ON","DIRLIGHTMAP_COMBINED","DYNAMICLIGHTMAP_ON","SHADOWS_SCREEN","SHADOWS_SHADOWMASK"],0],[["DIRECTIONAL","VERTEXLIGHT_ON","SHADOWS_SCREEN","SHADOWS_SHADOWMASK","LIGHTMAP_SHADOW_MIXING"],0],[["DIRECTIONAL","VERTEXLIGHT_ON","SHADOWS_SCREEN","SHADOWS_SHADOWMASK","LIGHTMAP_SHADOW_MIXING","LIGHTPROBE_SH"],0],[["DIRECTIONAL","VERTEXLIGHT_ON","DYNAMICLIGHTMAP_ON","SHADOWS_SCREEN","SHADOWS_SHADOWMASK","LIGHTMAP_SHADOW_MIXING"],0],[["DIRECTIONAL","VERTEXLIGHT_ON","DIRLIGHTMAP_COMBINED","DYNAMICLIGHTMAP_ON","SHADOWS_SCREEN","SHADOWS_SHADOWMASK","LIGHTMAP_SHADOW_MIXING"],0]],[[0,0,["DIRECTIONAL"],173,174,0,0],[0,0,["DIRECTIONAL"],175,176,1,0],[0,0,["DIRECTIONAL","LIGHTPROBE_SH"],177,178,0,0],[0,0,["DIRECTIONAL","LIGHTPROBE_SH"],179,180,1,0],[0,0,["DIRECTIONAL","SHADOWS_SCREEN"],181,182,0,0],[0,0,["DIRECTIONAL","SHADOWS_SCREEN"],183,184,1,0],[0,0,["DIRECTIONAL","LIGHTPROBE_SH","SHADOWS_SCREEN"],185,186,0,0],[0,0,["DIRECTIONAL","LIGHTPROBE_SH","SHADOWS_SCREEN"],187,188,1,0],[0,0,["DIRECTIONAL","_EMISSION"],173,189,0,0],[0,0,["DIRECTIONAL","_EMISSION"],175,190,1,0],[0,0,["DIRECTIONAL","LIGHTPROBE_SH","_EMISSION"],177,191,0,0],[0,0,["DIRECTIONAL","LIGHTPROBE_SH","_EMISSION"],179,192,1,0],[0,0,["DIRECTIONAL","SHADOWS_SCREEN","_EMISSION"],181,193,0,0],[0,0,["DIRECTIONAL","SHADOWS_SCREEN","_EMISSION"],183,194,1,0],[0,0,["DIRECTIONAL","LIGHTPROBE_SH","SHADOWS_SCREEN","_EMISSION"],185,195,0,0],[0,0,["DIRECTIONAL","LIGHTPROBE_SH","SHADOWS_SCREEN","_EMISSION"],187,196,1,0]],[],0],[1,0,"FORWARD_DELTA",5,"",0,[4,null],[0,null],[2,null],[[0,"_SrcBlend"],[1,null],[0,null]],[[0,"_SrcBlend"],[1,null],[0,null]],[15,null],[0,null],[0,null],[0,null],[255,null],[255,null],[[0,null],[0,null],[0,null],[8,null]],[[0,null],[0,null],[0,null],[8,null]],[[0,null],[0,null],[0,null],[8,null]],[["LIGHTMODE","FORWARDADD"],["PerformanceChecks","False"],["RenderType","Opaque"],["SHADOWSUPPORT","true"]],["DIRECTIONAL","DIRECTIONAL_COOKIE","FOG_EXP","FOG_EXP2","FOG_LINEAR","LIGHTMAP_SHADOW_MIXING","POINT","POINT_COOKIE","SHADOWS_CUBE","SHADOWS_DEPTH","SHADOWS_SCREEN","SHADOWS_SHADOWMASK","SHADOWS_SOFT","SPOT","STEREO_CUBEMAP_RENDER_ON","STEREO_INSTANCING_ON","STEREO_MULTIVIEW_ON","UNITY_SINGLE_PASS_STEREO","_ALPHABLEND_ON","_ALPHAPREMULTIPLY_ON","_ALPHATEST_ON","_DETAIL_MULX2","_METALLICGLOSSMAP","_NORMALMAP","_PARALLAXMAP","_SMOOTHNESS_TEXTURE_ALBEDO_CHANNEL_A","_SPECULARHIGHLIGHTS_OFF","__","_"],[[["__","FOG_LINEAR","FOG_EXP","FOG_EXP2"],1],[["_","_NORMALMAP"],1],[["_","_ALPHATEST_ON","_ALPHABLEND_ON","_ALPHAPREMULTIPLY_ON"],1],[["_","_METALLICGLOSSMAP"],1],[["_","_PARALLAXMAP"],1],[["POINT"],0],[["DIRECTIONAL"],0],[["SPOT"],0],[["POINT_COOKIE"],0],[["DIRECTIONAL_COOKIE"],0],[["POINT","SHADOWS_SHADOWMASK"],0],[["DIRECTIONAL","SHADOWS_SHADOWMASK"],0],[["SPOT","SHADOWS_SHADOWMASK"],0],[["POINT_COOKIE","SHADOWS_SHADOWMASK"],0],[["DIRECTIONAL_COOKIE","SHADOWS_SHADOWMASK"],0],[["POINT","SHADOWS_SHADOWMASK","LIGHTMAP_SHADOW_MIXING"],0],[["DIRECTIONAL","SHADOWS_SHADOWMASK","LIGHTMAP_SHADOW_MIXING"],0],[["SPOT","SHADOWS_SHADOWMASK","LIGHTMAP_SHADOW_MIXING"],0],[["POINT_COOKIE","SHADOWS_SHADOWMASK","LIGHTMAP_SHADOW_MIXING"],0],[["DIRECTIONAL_COOKIE","SHADOWS_SHADOWMASK","LIGHTMAP_SHADOW_MIXING"],0],[["SPOT","SHADOWS_DEPTH"],0],[["SPOT","SHADOWS_DEPTH","SHADOWS_SOFT"],0],[["SPOT","SHADOWS_DEPTH","LIGHTMAP_SHADOW_MIXING"],0],[["SPOT","SHADOWS_DEPTH","SHADOWS_SOFT","LIGHTMAP_SHADOW_MIXING"],0],[["SPOT","SHADOWS_DEPTH","SHADOWS_SHADOWMASK"],0],[["SPOT","SHADOWS_DEPTH","SHADOWS_SOFT","SHADOWS_SHADOWMASK"],0],[["SPOT","SHADOWS_DEPTH","SHADOWS_SHADOWMASK","LIGHTMAP_SHADOW_MIXING"],0],[["SPOT","SHADOWS_DEPTH","SHADOWS_SOFT","SHADOWS_SHADOWMASK","LIGHTMAP_SHADOW_MIXING"],0],[["DIRECTIONAL","SHADOWS_SCREEN"],0],[["DIRECTIONAL_COOKIE","SHADOWS_SCREEN"],0],[["DIRECTIONAL","SHADOWS_SCREEN","LIGHTMAP_SHADOW_MIXING"],0],[["DIRECTIONAL_COOKIE","SHADOWS_SCREEN","LIGHTMAP_SHADOW_MIXING"],0],[["DIRECTIONAL","SHADOWS_SCREEN","SHADOWS_SHADOWMASK"],0],[["DIRECTIONAL_COOKIE","SHADOWS_SCREEN","SHADOWS_SHADOWMASK"],0],[["DIRECTIONAL","SHADOWS_SCREEN","SHADOWS_SHADOWMASK","LIGHTMAP_SHADOW_MIXING"],0],[["DIRECTIONAL_COOKIE","SHADOWS_SCREEN","SHADOWS_SHADOWMASK","LIGHTMAP_SHADOW_MIXING"],0],[["POINT","SHADOWS_CUBE"],0],[["POINT","SHADOWS_CUBE","SHADOWS_SOFT"],0],[["POINT","SHADOWS_CUBE","LIGHTMAP_SHADOW_MIXING"],0],[["POINT","SHADOWS_CUBE","SHADOWS_SOFT","LIGHTMAP_SHADOW_MIXING"],0],[["POINT","SHADOWS_CUBE","SHADOWS_SHADOWMASK"],0],[["POINT","SHADOWS_CUBE","SHADOWS_SOFT","SHADOWS_SHADOWMASK"],0],[["POINT","SHADOWS_CUBE","SHADOWS_SHADOWMASK","LIGHTMAP_SHADOW_MIXING"],0],[["POINT","SHADOWS_CUBE","SHADOWS_SOFT","SHADOWS_SHADOWMASK","LIGHTMAP_SHADOW_MIXING"],0],[["POINT_COOKIE","SHADOWS_CUBE"],0],[["POINT_COOKIE","SHADOWS_CUBE","SHADOWS_SOFT"],0],[["POINT_COOKIE","SHADOWS_CUBE","LIGHTMAP_SHADOW_MIXING"],0],[["POINT_COOKIE","SHADOWS_CUBE","SHADOWS_SOFT","LIGHTMAP_SHADOW_MIXING"],0],[["POINT_COOKIE","SHADOWS_CUBE","SHADOWS_SHADOWMASK"],0],[["POINT_COOKIE","SHADOWS_CUBE","SHADOWS_SOFT","SHADOWS_SHADOWMASK"],0],[["POINT_COOKIE","SHADOWS_CUBE","SHADOWS_SHADOWMASK","LIGHTMAP_SHADOW_MIXING"],0],[["POINT_COOKIE","SHADOWS_CUBE","SHADOWS_SOFT","SHADOWS_SHADOWMASK","LIGHTMAP_SHADOW_MIXING"],0]],[[1,0,["DIRECTIONAL"],197,198,0,0],[1,0,["DIRECTIONAL"],199,200,1,0],[1,0,["DIRECTIONAL","SHADOWS_SCREEN"],201,202,0,0],[1,0,["DIRECTIONAL","SHADOWS_SCREEN"],203,204,1,0]],[],0],[2,0,"ShadowCaster",8,"",0,[4,null],[1,null],[2,null],[[1,null],[0,null],[0,null]],[[1,null],[0,null],[0,null]],[15,null],[0,null],[0,null],[0,null],[255,null],[255,null],[[0,null],[0,null],[0,null],[8,null]],[[0,null],[0,null],[0,null],[8,null]],[[0,null],[0,null],[0,null],[8,null]],[["LIGHTMODE","SHADOWCASTER"],["PerformanceChecks","False"],["RenderType","Opaque"],["SHADOWSUPPORT","true"]],["INSTANCING_ON","SHADOWS_CUBE","SHADOWS_DEPTH","STEREO_CUBEMAP_RENDER_ON","STEREO_INSTANCING_ON","STEREO_MULTIVIEW_ON","UNITY_SINGLE_PASS_STEREO","_ALPHABLEND_ON","_ALPHAPREMULTIPLY_ON","_ALPHATEST_ON","_METALLICGLOSSMAP","_PARALLAXMAP","_SMOOTHNESS_TEXTURE_ALBEDO_CHANNEL_A","__","_"],[[["__","INSTANCING_ON"],1],[["_","_ALPHATEST_ON","_ALPHABLEND_ON","_ALPHAPREMULTIPLY_ON"],1],[["_","_METALLICGLOSSMAP"],1],[["_","_PARALLAXMAP"],1],[["SHADOWS_DEPTH"],0],[["SHADOWS_CUBE"],0]],[[2,0,["SHADOWS_DEPTH"],34,35,0,0],[2,0,["SHADOWS_DEPTH"],36,37,1,0]],[],0]],[],[["_Color",0,1,1,1,1,"",0],["_MainTex",4,0,0,0,0,"white",0],["_Cutoff",3,0.5,0,1,0,"",0],["_Glossiness",3,0.5,0,1,0,"",0],["_GlossMapScale",3,1,0,1,0,"",0],["_SmoothnessTextureChannel",2,0,0,0,0,"",0],["_Metallic",3,0,0,1,0,"",32],["_MetallicGlossMap",4,0,0,0,0,"white",0],["_SpecularHighlights",2,1,0,0,0,"",0],["_GlossyReflections",2,1,0,0,0,"",0],["_BumpScale",2,1,0,0,0,"",0],["_BumpMap",4,0,0,0,0,"bump",8],["_Parallax",3,0.0199999995529652,0.00499999988824129,0.0799999982118607,0,"",0],["_ParallaxMap",4,0,0,0,0,"black",0],["_OcclusionStrength",3,1,0,1,0,"",0],["_OcclusionMap",4,0,0,0,0,"white",0],["_EmissionColor",0,0,0,0,1,"",0],["_EmissionMap",4,0,0,0,0,"white",0],["_DetailMask",4,0,0,0,0,"white",0],["_DetailAlbedoMap",4,0,0,0,0,"grey",0],["_DetailNormalMapScale",2,1,0,0,0,"",0],["_DetailNormalMap",4,0,0,0,0,"bump",8],["_UVSec",2,0,0,0,0,"",0],["_Mode",2,0,0,0,0,"",1],["_SrcBlend",2,1,0,0,0,"",1],["_DstBlend",2,0,0,0,0,"",1],["_ZWrite",2,1,0,0,0,"",1]],19,70,0,0,0,0]}],"sprites":[{"id":750,"path":"Resources/unity_builtin_extra\\Background","assetBundleId":-2,"data":["Background",20,748,[0,0,0,0.08,0.08,0],[0.05,0.08,0,0.8125,1,0.08,-0.08,0,1,0,0.08,0.075,0,1,0.96875,-0.07,0.08,0,0.0625,1,-0.075,-0.08,0,0.03124997,0,-0.08,0.07,0,0,0.9375,-0.08,-0.05,0,0,0.1875],[6,5,4,3,4,5,1,4,3,0,1,3,2,1,0],-0.000835968181490898,-0.00160364620387554,0.999164044857025,0.998396337032318,0,0,1,1,0.3125,0.3125,0.3125,0.3125,[0,0,0,0],[-0.08,-0.08,0.08,0.08],200,32,32,32,32,16,16,0.0267509818077087,0.0513166785240173]},{"id":754,"path":"Resources/unity_builtin_extra\\InputFieldBackground","assetBundleId":-2,"data":["InputFieldBackground",20,752,[0,0,0,0.08,0.08,0],[0.05,0.08,0,0.8125,1,0.08,-0.08,0,1,0,0.08,0.075,0,1,0.96875,-0.07,0.08,0,0.0625,1,-0.075,-0.08,0,0.03124997,0,-0.08,0.07,0,0,0.9375,-0.08,-0.05,0,0,0.1875],[6,5,4,3,4,5,1,4,3,0,1,3,2,1,0],-0.000835968181490898,-0.00160364620387554,0.999164044857025,0.998396337032318,0,0,1,1,0.3125,0.3125,0.3125,0.3125,[0,0,0,0],[-0.08,-0.08,0.08,0.08],200,32,32,32,32,16,16,0.0267509818077087,0.0513166785240173]}],"textures":[{"id":720,"type":0,"path":"Resources/unity_builtin_extra\\Default-Particle","assetBundleId":-2,"data":["Default-Particle",64,64,7,1,1,0,4,0,0,1,4,1,1,0,0]},{"id":748,"type":0,"path":"Resources/unity_builtin_extra\\Background","assetBundleId":-2,"data":["Background",32,32,6,16,1,0,4,1,1,1,4,1,1,1,1]},{"id":752,"type":0,"path":"Resources/unity_builtin_extra\\InputFieldBackground","assetBundleId":-2,"data":["InputFieldBackground",32,32,6,16,1,0,4,1,1,1,4,1,1,1,1]}],"cubemaps":[{"id":27890,"type":2,"path":"Assets/Scenes/DevelopmentScene.unity/PrefilteredEnvironment.exr","assetBundleId":-2,"data":["",-227816,8,0,128,0,2,[0,0,0.25,0.5,0,0.5,0.25,1,0.25,0,0.5,0.5,0.25,0.5,0.5,1,0.5,0,0.75,0.5,0.75,0,1,0.5,0.5,0.5,0.625,0.75,0.5,0.75,0.625,1,0.625,0.5,0.75,0.75,0.625,0.75,0.75,1,0.75,0.5,0.875,0.75,0.875,0.5,1,0.75,0.75,0.75,0.8125,0.875,0.75,0.875,0.8125,1,0.8125,0.75,0.875,0.875,0.8125,0.875,0.875,1,0.875,0.75,0.9375,0.875,0.9375,0.75,1,0.875,0.875,0.875,0.90625,0.9375,0.875,0.9375,0.90625,1,0.90625,0.875,0.9375,0.9375,0.90625,0.9375,0.9375,1,0.9375,0.875,0.96875,0.9375,0.96875,0.875,1,0.9375,0.9375,0.9375,0.953125,0.96875,0.9375,0.96875,0.953125,1,0.953125,0.9375,0.96875,0.96875,0.953125,0.96875,0.96875,1,0.96875,0.9375,0.984375,0.96875,0.984375,0.9375,1,0.96875,0.96875,0.96875,0.9765625,0.984375,0.96875,0.984375,0.9765625,1,0.9765625,0.96875,0.984375,0.984375,0.9765625,0.984375,0.984375,1,0.984375,0.96875,0.9921875,0.984375,0.9921875,0.96875,1,0.984375,0.984375,0.984375,0.98828125,0.9921875,0.984375,0.9921875,0.98828125,1,0.98828125,0.984375,0.9921875,0.9921875,0.98828125,0.9921875,0.9921875,1,0.9921875,0.984375,0.99609375,0.9921875,0.99609375,0.984375,1,0.9921875,0.9921875,0.9921875,0.994140625,0.99609375,0.9921875,0.99609375,0.994140625,1,0.994140625,0.9921875,0.99609375,0.99609375,0.994140625,0.99609375,0.99609375,1,0.99609375,0.9921875,0.998046875,0.99609375,0.998046875,0.9921875,1,0.99609375],1,1]}],"resources":[{"id":0,"assetBundleId":-2,"data":[[["unity_builtin_extra",19,26],["unity_builtin_extra",15,518],["unity_builtin_extra",19,178],["fonts & materials/liberationsans sdf",20,24824],["fonts & materials/liberationsans sdf",15,24822],["fonts & materials/liberationsans sdf - fallback",20,24646],["fonts & materials/liberationsans sdf - fallback",15,24644],["fonts & materials/liberationsans sdf - fallback",31,24642],["fonts & materials/liberationsans sdf",31,24820],["unity_builtin_extra",19,170],["unity_builtin_extra",20,720],["unity_builtin_extra",15,722],["unity_builtin_extra",19,66],["unity_builtin_extra",15,726],["unity_builtin_extra",20,748],["unity_builtin_extra",17,750],["unity_builtin_extra",20,752],["unity_builtin_extra",17,754],["unity_builtin_extra",15,732],["unity_builtin_extra",19,152],["unity_builtin_extra",15,728],["unity_builtin_extra",19,28],["dotweensettings",85,24838],["sprite assets/emojione",15,27682],["sprite assets/emojione",87,24434],["style sheets/default style sheet",88,24418],["linebreaking leading characters",89,27678],["linebreaking following characters",89,27680],["tmp settings",86,24696]],[27460,26128,27566,26128,27582,26128,27524,26128,27520,26128,27490,26128,27480,26128,27564,26128,27588,26128,27562,26128,27504,26128,27492,26128,27546,26128,27624,26128,27544,26128,27548,26128,27552,26128,27550,26128,27554,26128,27560,26128,27556,26128,27540,26128,27596,26128,27542,26128,27530,26128,27628,26128,27528,26128,27532,26128,27536,26128,27534,26128,27538,26128,27558,26128,27512,26128,27494,26128,27478,26128,26134,26128,26138,26128,27474,26128,27470,27484,27464,27484,27508,27484,27458,26128,27462,26128,27448,26128,27456,26128,26130,26128,-226802,-226782,27506,26128,-226830,-226782,-226834,-226782,-226826,-226782,-226822,-226782,-226818,-226782,-226814,-226782,-226850,-226782,-226854,-226782,-226846,-226782,-226842,-226782,-226838,-226782,-226894,-226782,-226898,-226782,-226890,-226782,-226886,-226782,-226882,-226782,-226878,-226782,-226874,-226782,-226870,-226782,-226866,-226782,-226906,-226782,-226910,-226782,-226902,-226782,-226938,-226782,-226942,-226782,-226934,-226782,-226930,-226782,-226926,-226782,-226922,-226782,-226918,-226782,-226914,-226782,-226862,-226782,-226858,-226782,-226808,-226782,32364,-226782,27500,26128,31772,-226782,27514,26128,27516,26128,-226952,-226782,27486,26128,-226946,-226782,-226960,-226782,-226792,-226782,26116,26112,27432,26112,27434,26112,31728,32144,26120,26112,27438,26112,26122,26112,27436,26112,-227200,32144,-227208,32144,26118,26112,27430,26112,26180,26178,27634,26178,27636,26178,31858,32144,26186,26178,26188,26178,26182,26178,26192,26178,-227220,32144,-227228,32144,26184,26178,26190,26178,32202,32144,27134,27126,27186,27126,27168,27126,27176,27126,27164,27126,27190,27126,27192,27126,27172,27126,27178,27126,27146,27126,27160,27126,26220,26224,27228,27126,27230,27126,27224,27126,27226,27126,27204,27126,27202,27126,27242,26224,27244,26224,27246,26224,27248,26224,27250,26224,27148,27126,27252,26224,27254,26224,27256,26224,27238,26224,26218,26224,27158,27126,32018,32144,27276,26224,27274,26224,27280,26224,27278,26224,27266,26224,27268,26224,-227264,32144,-227272,32144,-227280,32144,-227288,32144,-227296,32144,26222,26224,-227268,32144,-227276,32144,-227292,32144,-227258,32144,-227284,32144,27240,26224,26234,26232,27440,26232,32322,32144,26236,26232,26242,26232,-227308,32144,26238,26232,26240,26232,32324,32144,26198,26196,27114,26196,27116,26196,31888,32144,26202,26196,27122,26196,26204,26196,27124,26196,-227240,32144,-227248,32144,26200,26196,27112,26196,31890,32144,26580,26560,26656,26560,26604,26560,26608,26560,26660,26560,26644,26560,26636,26560,26640,26560,26648,26560,26632,26560,26628,26560,26652,26560,26592,26560,26600,26560,26672,26560,26616,26560,26620,26560,26664,26560,26760,26560,26764,26560,26624,26560,26588,26560,26612,26560,26596,26560,26054,26082,26854,26560,26872,26560,26876,26560,26866,26560,26818,26560,27292,26082,26864,26560,26822,26560,26816,26560,26814,26560,26824,26560,26844,26560,26830,26560,26828,26560,26882,26560,26860,26560,26874,26560,26848,26560,26834,26560,26842,26560,26806,26560,26810,26560,26868,26560,26832,26560,26802,26560,26862,26560,26852,26560,26808,26560,26850,26560,26826,26560,26804,26560,26878,26560,26840,26560,26880,26560,26798,26560,26870,26560,26080,26082,26052,26082,26102,26082,26096,26082,26092,26082,26094,26082,26098,26082,26088,26082,26086,26082,26100,26082,26076,26082,26050,26082,26104,26082,26084,26082,26048,26082,26812,26560,26846,26560,26078,26082,27296,26082,26884,26560,26886,26560,27338,26082,27340,26082,27342,26082,26230,26082,26214,26082,27290,26082,27294,26082,26574,26560,26578,26560,26570,26560,31604,32144,27370,26082,27372,26082,27362,26082,27364,26082,27398,26082,-227342,32144,27416,26082,27418,26082,27346,26082,27348,26082,27374,26082,27376,26082,27350,26082,27352,26082,27408,26082,27410,26082,27378,26082,27380,26082,27354,26082,27356,26082,27404,26082,27406,26082,27366,26082,27368,26082,27388,26082,27390,26082,27392,26082,27394,26082,27384,26082,27386,26082,27358,26082,27360,26082,27412,26082,27414,26082,27420,26082,27422,26082,32128,32144,31602,32144,31734,32144,32212,32144,31768,32144,32178,32144,32196,32144,-227388,32144,32142,32144,32104,32144,32238,32144,31600,32144,31892,32144,31776,32144,31598,32144,27396,26082,26090,26082,-227320,32144,-227446,32144,27426,26082,27428,26082,27424,26082,-227450,32144,-227456,32144,-227462,32144,32250,32144,31952,32144,-227336,32144,-227438,32144,27286,26082,27288,26082,26142,26152,26582,26152,26148,26152,26150,26152,26172,26152,26166,26152,26162,26152,26164,26152,26168,26152,26160,26152,26158,26152,26170,26152,26144,26152,26146,26152,26174,26152,26154,26152,26156,26152,26568,26152,26586,26152,26668,26152,26670,26152,26216,26152,26572,26152,26246,26152,26584,26152,31792,32144,26718,26152,26720,26152,26704,26152,26706,26152,26758,26152,-227494,32144,26788,26152,26790,26152,26680,26152,26682,26152,26724,26152,26726,26152,26686,26152,26688,26152,26776,26152,26778,26152,26730,26152,26732,26152,26692,26152,26694,26152,26770,26152,26772,26152,26710,26152,26712,26152,26742,26152,26744,26152,26748,26152,26750,26152,26736,26152,26738,26152,26698,26152,26700,26152,26782,26152,26784,26152,26794,26152,26796,26152,-227498,32144,-227506,32144,-227514,32144,-227522,32144,-227530,32144,-227538,32144,-227546,32144,-227554,32144,-227562,32144,-227570,32144,-227578,32144,-227586,32144,-227594,32144,-227602,32144,-227610,32144,26754,26152,26228,26152,-227472,32144,-227624,32144,26838,26152,26858,26152,-227628,32144,-227634,32144,31970,32144,-227482,32144,32334,32144,-227618,32144,26564,26152,26566,26152,26058,26062,27136,26062,27138,26062,27140,26062,27142,26062,27144,26062,27150,26062,27152,26062,27154,26062,27130,26062,26056,26062,31608,32144,27210,26062,27200,26062,27218,26062,27214,26062,27182,26062,27184,26062,-226976,32144,-226984,32144,-226992,32144,-227000,32144,-227008,32144,26060,26062,-226980,32144,-226988,32144,-227004,32144,-226970,32144,-226996,32144,27132,26062,26992,26998,26994,26998,27004,26998,26258,26256,27084,26998,27080,26998,26944,26256,26928,26256,26986,26998,26988,26998,26910,26256,27052,26998,27050,26998,26940,26998,26268,26256,26912,26256,26946,26256,26948,26256,27008,26256,27022,26256,26262,26256,27024,26256,26266,26256,27040,26256,26918,26256,26956,26256,26964,26256,26250,26256,26924,26256,26960,26256,26274,26256,26968,26256,27010,26256,26972,26256,26914,26256,27016,26256,27060,26256,26920,26256,27090,26256,27018,26256,26894,26256,26140,26256,26900,26256,26902,26256,26904,26256,26906,26256,26908,26256,-227044,-227014,27046,26256,27048,26256,-227052,-227014,-227036,-227014,26936,26256,26938,26256,-227028,-227014,27000,26256,27002,26256,-227016,-227014,27006,26256,26260,26256,-227060,-227014,27032,26256,27034,26256,27028,26256,-227068,-227014,-227076,-227014,26950,26256,26952,26256,-227092,-227014,27096,26256,27098,26256,-227106,-227014,27036,26256,27038,26256,-227110,-227014,-227118,-227014,27030,26256,-227122,-227014,-227098,-227014,-227088,-227014,-227126,-227014,26980,26256,26970,26256,-227142,-227014,-227024,-227014,27026,26256,-227152,-227014,26974,26256,-227162,-227014,-227130,-227014,-227138,-227014,-227148,-227014,-227158,-227014,-227084,-227014,-227172,-227014,27100,26256,27102,26256,-227178,-227014,-227168,-227014,27078,26256,27088,26256,27092,26256,-227190,-227014,-227186,-227014,26248,26256,26890,26256,26892,26256,-227080,-227014,31774,-227014,-227094,-227014,-227134,-227014,-227154,-227014,-227164,-227014,-227144,-227014,-226962,-226782,26132,26128,-226784,-226782,27444,26128,27446,26128,27450,26128,27452,26128,27454,26128,26328,26208,26412,26208,26512,26208,26410,26208,26414,26208,26380,26208,26356,26208,26408,26208,26506,26208,26406,26208,26404,26208,26362,26208,26384,26208,26554,26208,26382,26208,26386,26208,26390,26208,26388,26208,26392,26208,26398,26208,26394,26208,26376,26208,26522,26208,26378,26208,26366,26208,26550,26208,26364,26208,26368,26208,26372,26208,26370,26208,26374,26208,26396,26208,26402,26208,26400,26208,26354,26208,26304,26208,26330,26208,26306,26208,26332,26208,26316,26210,26418,26446,26452,26446,26336,26210,26494,26446,26496,26446,26424,26210,26480,26446,26482,26446,26428,26460,26440,26460,26334,26210,26338,26210,26322,26212,26342,26212,26344,26212,26326,26212,26346,26212,26340,26212,32036,32144]]}],"project-settings":[{"id":-1,"assetBundleId":-2,"data":[[["UnityEngine.EventSystems.EventSystem",-1000],["UnityEngine.UI.ToggleGroup",10],["Cinemachine.CinemachinePixelPerfect",-1],["TMPro.TextMeshPro",-105],["Cinemachine.CinemachineIndependentImpulseListener",200],["Cinemachine.CinemachineBrain",100],["TMPro.TextMeshProUGUI",-100],["TMPro.TextContainer",-110]],[[0,"Default",0]],[[0,"Default"],[1,"TransparentFX"],[2,"Ignore Raycast"],[3,"Obstacle"],[4,"Water"],[5,"UI"],[6,"Board"]],[0.0199999995529652,0.333333343267441,1,0.0299999993294477],[0,-9.8100004196167,0,6,2,0,1,[[0,0,0],[0,0,1],[0,0,2],[0,0,3],[0,0,4],[0,0,5],[0,0,6],[0,1,0],[0,1,1],[0,1,2],[0,1,3],[0,1,4],[0,1,5],[0,1,6],[0,2,0],[0,2,1],[0,2,2],[0,2,3],[0,2,4],[0,2,5],[0,2,6],[0,3,0],[0,3,1],[0,3,2],[0,3,3],[0,3,4],[0,3,5],[0,3,6],[0,4,0],[0,4,1],[0,4,2],[0,4,3],[0,4,4],[0,4,5],[0,4,6],[0,5,0],[0,5,1],[0,5,2],[0,5,3],[0,5,4],[0,5,5],[0,5,6],[0,6,0],[0,6,1],[0,6,2],[0,6,3],[0,6,4],[0,6,5],[0,6,6]]],[null,null,0,-9.8100004196167,3,8,1,0.200000002980232,8,100,360,0.200000002980232,0.75,0.5,0.00999999977648258,2,0.00999999977648258,1,1,1,1,1,0,[[0,0,0],[0,0,1],[0,0,2],[0,0,3],[0,0,4],[0,0,5],[0,0,6],[0,1,0],[0,1,1],[0,1,2],[0,1,3],[0,1,4],[0,1,5],[0,1,6],[0,2,0],[0,2,1],[0,2,2],[0,2,3],[0,2,4],[0,2,5],[0,2,6],[0,3,0],[0,3,1],[0,3,2],[0,3,3],[0,3,4],[0,3,5],[0,3,6],[0,4,0],[0,4,1],[0,4,2],[0,4,3],[0,4,4],[0,4,5],[0,4,6],[0,5,0],[0,5,1],[0,5,2],[0,5,3],[0,5,4],[0,5,5],[0,5,6],[0,6,0],[0,6,1],[0,6,2],[0,6,3],[0,6,4],[0,6,5],[0,6,6]]],[[[[],["Very Low","Low","Medium","High","Very High","Ultra"],0,0,0,0.300000011920929,1,15,0,1,0,0,0,1,1,1,2,4,0,0,0.333333343267441,0.0666666701436043,0.200000002980232,0.466666668653488,0,0,16,2,0,3,512,0,1,2,512,1,1024,0],[[],["Very Low","Low","Medium","High","Very High","Ultra"],0,0,0,0.400000005960464,1,20,0,1,0,0,0,1,1,0,2,16,0,0,0.333333343267441,0.0666666701436043,0.200000002980232,0.466666668653488,0,0,16,2,0,3,512,0,1,2,512,1,1024,1],[[],["Very Low","Low","Medium","High","Very High","Ultra"],1,1,0,0.699999988079071,1,20,0,1,0,0,0,1,1,0,2,64,1,0,0.333333343267441,0.0666666701436043,0.200000002980232,0.466666668653488,0,1,16,2,0,3,512,0,1,2,512,1,1024,2],[[],["Very Low","Low","Medium","High","Very High","Ultra"],2,1,0,1,2,40,1,1,1,0,1,1,1,0,2,256,2,1,0.333333343267441,0.0666666701436043,0.200000002980232,0.466666668653488,0,1,16,2,1,3,512,0,1,2,512,1,1024,3],[[],["Very Low","Low","Medium","High","Very High","Ultra"],2,2,2,1.5,2,70,1,1,2,1,1,1,1,0,2,1024,3,1,0.333333343267441,0.0666666701436043,0.200000002980232,0.466666668653488,0,1,16,2,1,3,512,0,1,2,512,1,1024,4],[[],["Very Low","Low","Medium","High","Very High","Ultra"],2,2,2,2,4,150,1,1,2,1,1,1,1,0,2,4096,4,1,0.333333343267441,0.0666666701436043,0.200000002980232,0.466666668653488,0,1,16,2,1,3,512,0,1,2,512,1,1024,5]],["Very Low","Low","Medium","High","Very High","Ultra"],2,2,2,2,4,150,1,1,2,1,1,1,1,0,2,4096,4,1,0.333333343267441,0.0666666701436043,0.200000002980232,0.466666668653488,0,1,16,2,1,3,512,0,1,2,512,1,1024,5],0,0,0,0,2,1,["Untagged","Respawn","Finish","EditorOnly","MainCamera","Player","GameController"]]}]}